[{"datasetObjectId":"15","consolidatedAnnotation":{"content":{"Labels":{"image_size":[{"width":1536,"height":2048,"depth":3}],"annotations":[{"class_id":0,"top":341,"left":825,"height":6,"width":7},{"class_id":0,"top":329,"left":601,"height":4,"width":8},{"class_id":0,"top":124,"left":621,"height":8,"width":12},{"class_id":0,"top":92,"left":715,"height":10,"width":7},{"class_id":1,"top":1947,"left":721,"height":31,"width":24},{"class_id":1,"top":1877,"left":720,"height":19,"width":7},{"class_id":1,"top":970,"left":668,"height":13,"width":13},{"class_id":1,"top":993,"left":692,"height":28,"width":14},{"class_id":1,"top":1262,"left":703,"height":29,"width":26},{"class_id":1,"top":1255,"left":739,"height":18,"width":11},{"class_id":1,"top":699,"left":697,"height":27,"width":17},{"class_id":1,"top":756,"left":706,"height":27,"width":17},{"class_id":1,"top":642,"left":697,"height":18,"width":20},{"class_id":1,"top":540,"left":703,"height":19,"width":14}]},"Labels-metadata":{"objects":[{"confidence":0.0},{"confidence":0.0},{"confidence":0.0},{"confidence":0.0},{"confidence":0.0},{"confidence":0.0},{"confidence":0.0},{"confidence":0.0},{"confidence":0.0},{"confidence":0.0},{"confidence":0.0},{"confidence":0.0},{"confidence":0.0},{"confidence":0.0}],"class-map":{"0":"hole","1":"no_hole"},"type":"groundtruth/object-detection","human-annotated":"yes","creation-date":"2021-05-12T00:00:05.544346","job-name":"labeling-job/aws-workshops-woodpecker-holes-v5"}}}},{"datasetObjectId":"5","consolidatedAnnotation":{"content":{"Labels":{"image_size":[{"width":3024,"height":4032,"depth":3}],"annotations":[{"class_id":0,"top":388,"left":1252,"height":32,"width":30},{"class_id":0,"top":1530,"left":1323,"height":59,"width":63},{"class_id":0,"top":1408,"left":1408,"height":29,"width":27},{"class_id":0,"top":1666,"left":1339,"height":34,"width":35},{"class_id":0,"top":2583,"left":1282,"height":65,"width":55},{"class_id":0,"top":2437,"left":1286,"height":43,"width":29},{"class_id":0,"top":2499,"left":1330,"height":32,"width":24},{"class_id":0,"top":2692,"left":1365,"height":29,"width":42},{"class_id":0,"top":1729,"left":1217,"height":36,"width":31},{"class_id":0,"top":972,"left":1377,"height":36,"width":38},{"class_id":0,"top":1398,"left":1325,"height":30,"width":14},{"class_id":0,"top":1444,"left":1330,"height":17,"width":11},{"class_id":0,"top":1321,"left":1428,"height":15,"width":10},{"class_id":0,"top":1889,"left":1268,"height":19,"width":12},{"class_id":0,"top":1918,"left":1270,"height":16,"width":12},{"class_id":0,"top":3572,"left":1325,"height":23,"width":20},{"class_id":0,"top":3520,"left":1271,"height":109,"width":29},{"class_id":0,"top":2693,"left":1403,"height":206,"width":31},{"class_id":0,"top":2535,"left":1390,"height":77,"width":26},{"class_id":0,"top":2171,"left":1356,"height":25,"width":23},{"class_id":1,"top":750,"left":1159,"height":204,"width":356},{"class_id":1,"top":387,"left":1485,"height":361,"width":138},{"class_id":1,"top":667,"left":1198,"height":82,"width":285},{"class_id":1,"top":1018,"left":1380,"height":236,"width":182},{"class_id":1,"top":1573,"left":1114,"height":722,"width":87},{"class_id":1,"top":2290,"left":1380,"height":192,"width":136},{"class_id":1,"top":2628,"left":1071,"height":99,"width":89}]},"Labels-metadata":{"objects":[{"confidence":0.0},{"confidence":0.0},{"confidence":0.0},{"confidence":0.0},{"confidence":0.0},{"confidence":0.0},{"confidence":0.0},{"confidence":0.0},{"confidence":0.0},{"confidence":0.0},{"confidence":0.0},{"confidence":0.0},{"confidence":0.0},{"confidence":0.0},{"confidence":0.0},{"confidence":0.0},{"confidence":0.0},{"confidence":0.0},{"confidence":0.0},{"confidence":0.0},{"confidence":0.0},{"confidence":0.0},{"confidence":0.0},{"confidence":0.0},{"confidence":0.0},{"confidence":0.0},{"confidence":0.0}],"class-map":{"0":"hole","1":"no_hole"},"type":"groundtruth/object-detection","human-annotated":"yes","creation-date":"2021-05-12T00:00:05.545616","job-name":"labeling-job/aws-workshops-woodpecker-holes-v5"}}}}]